{"cameraMode":{"drawMode":0,"name":"Shaded","section":"Shading Mode"},"sceneLighting":true,"audioPlay":false,"sceneViewState":{"m_AlwaysRefresh":false,"showFog":true,"showSkybox":true,"showFlares":true,"showImageEffects":true,"showParticleSystems":true,"showVisualEffectGraphs":true,"m_FxEnabled":true},"in2DMode":false,"pivot":{"x":-113.2262954711914,"y":5.377199172973633,"z":-3.952728271484375},"rotation":{"x":0.0081809526309371,"y":0.7142316102981567,"z":0.008350038900971413,"w":-0.6998043656349182},"size":48.76869583129883,"orthographic":false}